genderapi/__init__.py
genderapi-1.1.5.dist-info/METADATA
genderapi-1.1.5.dist-info/WHEEL
genderapi-1.1.5.dist-info/top_level.txt
genderapi-1.1.5.dist-info/RECORD
