Metadata-Version: 2.4
Name: genderapi
Version: 1.1.5
Summary: Official Python SDK for GenderAPI.io
Author-email: Onur Ozturk <support@genderapi.io>
License: MIT
Project-URL: Homepage, https://www.genderapi.io
Project-URL: Repository, https://github.com/GenderAPI/genderapi-python
Keywords: gender,api,genderapi,gender detection
Classifier: Programming Language :: Python :: 3
Classifier: License :: OSI Approved :: MIT License
Classifier: Operating System :: OS Independent
Requires-Python: >=3.7
Requires-Dist: requests<3.0.0,>=2.28.0
